LICENSE
MANIFEST.in
README.md
setup.py
django_fec_raw_data.egg-info/PKG-INFO
django_fec_raw_data.egg-info/SOURCES.txt
django_fec_raw_data.egg-info/dependency_links.txt
django_fec_raw_data.egg-info/requires.txt
django_fec_raw_data.egg-info/top_level.txt
fec_raw/__init__.py
fec_raw/admin.py
fec_raw/fech_filing.rb
fec_raw/fields.py
fec_raw/tests.py
fec_raw/management/__init__.py
fec_raw/management/commands/__init__.py
fec_raw/management/commands/downloadfecrawdata.py
fec_raw/management/commands/loadfecrawdata.py
fec_raw/models/__init__.py
fec_raw/models/filing.py
fec_raw/models/line_item.py