Metadata-Version: 1.1
Name: django-fec-raw-data
Version: 0.0.3
Summary: A Django app to download, extract and load campaign finance from the Federal Election Commission
Home-page: UNKNOWN
Author: The Los Angeles Times Data Desk
Author-email: datadesk@latimes.com
License: MIT
Platform: UNKNOWN
Classifier: Programming Language :: Python
Classifier: Programming Language :: Python :: 2.7
